anydi/__init__.py
anydi/_async_lock.py
anydi/_cli.py
anydi/_container.py
anydi/_context.py
anydi/_decorators.py
anydi/_graph.py
anydi/_injector.py
anydi/_marker.py
anydi/_module.py
anydi/_provider.py
anydi/_resolver.py
anydi/_scanner.py
anydi/_types.py
anydi/ext/__init__.py
anydi/ext/django/__init__.py
anydi/ext/fastapi.py
anydi/ext/faststream.py
anydi/ext/pydantic_settings.py
anydi/ext/pytest_plugin.py
anydi/ext/starlette/__init__.py
anydi/ext/starlette/middleware.py
anydi/ext/typer.py
anydi/py.typed
anydi/testing.py
anydi-0.70.2.dist-info/WHEEL
anydi-0.70.2.dist-info/entry_points.txt
anydi-0.70.2.dist-info/METADATA
anydi-0.70.2.dist-info/RECORD
