Metadata-Version: 2.4
Name: anydi
Version: 0.70.2
Summary: Dependency Injection library
Keywords: dependency injection,dependencies,di,async,asyncio,application
Author: Anton Ruhlov
Author-email: Anton Ruhlov <antonruhlov@gmail.com>
License-Expression: MIT
Classifier: Intended Audience :: Information Technology
Classifier: Intended Audience :: System Administrators
Classifier: Operating System :: OS Independent
Classifier: Development Status :: 5 - Production/Stable
Classifier: Topic :: Internet
Classifier: Topic :: Software Development :: Libraries :: Application Frameworks
Classifier: Topic :: Software Development :: Libraries :: Python Modules
Classifier: Topic :: Software Development :: Libraries
Classifier: Topic :: Software Development
Classifier: Typing :: Typed
Classifier: Environment :: Web Environment
Classifier: Intended Audience :: Developers
Classifier: License :: OSI Approved :: MIT License
Classifier: Programming Language :: Python :: 3
Classifier: Programming Language :: Python :: 3.10
Classifier: Programming Language :: Python :: 3.11
Classifier: Programming Language :: Python :: 3.12
Classifier: Programming Language :: Python :: 3.13
Classifier: Programming Language :: Python :: 3.14
Classifier: Programming Language :: Python :: 3 :: Only
Requires-Dist: typing-extensions>=4.15.0,<5
Requires-Dist: anyio>=3.7.1
Requires-Dist: wrapt>=1.17.0
Requires-Python: >=3.10.0, <3.15
Project-URL: Repository, https://github.com/antonrh/anydi
